{
  "date": "2026-06-14",
  "generated_at": "2026-06-14T20:37:03.589936+00:00",
  "predictions_available": true,
  "model_version": "v2.0-approach-c",
  "games": [
    {
      "game_pk": 823368,
      "home_team": "PIT",
      "away_team": "MIA",
      "venue": "PNC Park",
      "home_pitcher": "Paul Skenes",
      "away_pitcher": "Max Meyer",
      "game_time": "2026-06-14T16:15:00Z",
      "temperature_f": 77.3,
      "humidity_pct": 75.0,
      "wind_speed_mph": 7.4,
      "wind_carry_mph": 7.4,
      "air_density_index": 93.2,
      "dome_active": 0,
      "seasonal_pf_runs": 0.95,
      "daily_pf_runs": 0.9728,
      "daily_pf_hr": 0.958,
      "pf_weather_delta_runs": 0.0228,
      "pf_weather_delta_hr": -0.0395,
      "wind_venue_sensitivity": 1.0,
      "home_lineup_pf_hr": 2.783,
      "away_lineup_pf_hr": 2.759,
      "lineup_pf_hr_diff": 0.0237,
      "lineup_pf_hr_residual": 1.8251,
      "has_lineups": true,
      "home_lineup_status": "CONFIRMED",
      "away_lineup_status": "CONFIRMED",
      "win_prob_home": 0.497,
      "edge": 0.0459,
      "edge_side": "away",
      "recommendation": "PASS",
      "cgsi_tier": "LOW",
      "consensus_ratio": 0.17,
      "n_specialists_agree": 2
    },
    {
      "game_pk": 824823,
      "home_team": "BAL",
      "away_team": "SD",
      "venue": "Oriole Park at Camden Yards",
      "home_pitcher": "Trevor Rogers",
      "away_pitcher": "Walker Buehler",
      "game_time": "2026-06-14T17:35:00Z",
      "temperature_f": 90.4,
      "humidity_pct": 54.0,
      "wind_speed_mph": 10.1,
      "wind_carry_mph": 9.2,
      "air_density_index": 93.3,
      "dome_active": 0,
      "seasonal_pf_runs": 1.02,
      "daily_pf_runs": 1.1331,
      "daily_pf_hr": 1.3588,
      "pf_weather_delta_runs": 0.1131,
      "pf_weather_delta_hr": 0.2878,
      "wind_venue_sensitivity": 1.0,
      "home_lineup_pf_hr": 3.0,
      "away_lineup_pf_hr": 2.596,
      "lineup_pf_hr_diff": 0.4036,
      "lineup_pf_hr_residual": 1.6412,
      "has_lineups": true,
      "home_lineup_status": "CONFIRMED",
      "away_lineup_status": "CONFIRMED",
      "win_prob_home": 0.518,
      "edge": 0.0041,
      "edge_side": "home",
      "recommendation": "PASS",
      "cgsi_tier": "LOW",
      "consensus_ratio": 0.67,
      "n_specialists_agree": 8
    },
    {
      "game_pk": 822722,
      "home_team": "WSH",
      "away_team": "SEA",
      "venue": "Nationals Park",
      "home_pitcher": "PJ Poulin",
      "away_pitcher": "Emerson Hancock",
      "game_time": "2026-06-14T17:35:00Z",
      "temperature_f": 90.9,
      "humidity_pct": 48.0,
      "wind_speed_mph": 12.2,
      "wind_carry_mph": 11.2,
      "air_density_index": 93.3,
      "dome_active": 0,
      "seasonal_pf_runs": 0.99,
      "daily_pf_runs": 1.0968,
      "daily_pf_hr": 1.3285,
      "pf_weather_delta_runs": 0.1068,
      "pf_weather_delta_hr": 0.289,
      "wind_venue_sensitivity": 1.0,
      "home_lineup_pf_hr": 2.84,
      "away_lineup_pf_hr": 2.741,
      "lineup_pf_hr_diff": 0.0982,
      "lineup_pf_hr_residual": 1.5111,
      "has_lineups": true,
      "home_lineup_status": "CONFIRMED",
      "away_lineup_status": "CONFIRMED",
      "win_prob_home": 0.497,
      "edge": 0.0773,
      "edge_side": "home",
      "recommendation": "PASS",
      "cgsi_tier": "VERY_LOW",
      "consensus_ratio": 0.5,
      "n_specialists_agree": 6
    },
    {
      "game_pk": 822801,
      "home_team": "TOR",
      "away_team": "NYY",
      "venue": "Rogers Centre",
      "home_pitcher": "Patrick Corbin",
      "away_pitcher": "Will Warren",
      "game_time": "2026-06-14T17:37:00Z",
      "temperature_f": 63.9,
      "humidity_pct": 95.0,
      "wind_speed_mph": 4.6,
      "wind_carry_mph": 0.7,
      "air_density_index": 97.4,
      "dome_active": 0,
      "seasonal_pf_runs": 1.0,
      "daily_pf_runs": 0.9539,
      "daily_pf_hr": 1.1208,
      "pf_weather_delta_runs": -0.0461,
      "pf_weather_delta_hr": 0.0708,
      "wind_venue_sensitivity": 0.5,
      "home_lineup_pf_hr": 2.168,
      "away_lineup_pf_hr": 2.56,
      "lineup_pf_hr_diff": -0.3924,
      "lineup_pf_hr_residual": 1.047,
      "has_lineups": true,
      "home_lineup_status": "CONFIRMED",
      "away_lineup_status": "CONFIRMED",
      "win_prob_home": 0.497,
      "edge": 0.1127,
      "edge_side": "home",
      "recommendation": "PASS",
      "cgsi_tier": "LOW",
      "consensus_ratio": 0.17,
      "n_specialists_agree": 2
    },
    {
      "game_pk": 824506,
      "home_team": "CIN",
      "away_team": "ARI",
      "venue": "Great American Ball Park",
      "home_pitcher": "Andrew Abbott",
      "away_pitcher": "Zac Gallen",
      "game_time": "2026-06-14T17:40:00Z",
      "temperature_f": 79.5,
      "humidity_pct": 79.0,
      "wind_speed_mph": 11.9,
      "wind_carry_mph": -2.3,
      "air_density_index": 93.5,
      "dome_active": 0,
      "seasonal_pf_runs": 1.08,
      "daily_pf_runs": 1.1422,
      "daily_pf_hr": 1.2796,
      "pf_weather_delta_runs": 0.0622,
      "pf_weather_delta_hr": 0.1456,
      "wind_venue_sensitivity": 1.0,
      "home_lineup_pf_hr": 2.121,
      "away_lineup_pf_hr": 2.249,
      "lineup_pf_hr_diff": -0.1284,
      "lineup_pf_hr_residual": 0.8412,
      "has_lineups": true,
      "home_lineup_status": "CONFIRMED",
      "away_lineup_status": "CONFIRMED",
      "win_prob_home": 0.497,
      "edge": 0.0671,
      "edge_side": "home",
      "recommendation": "PASS",
      "cgsi_tier": "LOW",
      "consensus_ratio": 0.5,
      "n_specialists_agree": 6
    },
    {
      "game_pk": 823615,
      "home_team": "NYM",
      "away_team": "ATL",
      "venue": "Citi Field",
      "home_pitcher": "Freddy Peralta",
      "away_pitcher": "Bryce Elder",
      "game_time": "2026-06-14T17:40:00Z",
      "temperature_f": 88.1,
      "humidity_pct": 47.0,
      "wind_speed_mph": 15.2,
      "wind_carry_mph": 8.5,
      "air_density_index": 93.9,
      "dome_active": 0,
      "seasonal_pf_runs": 0.94,
      "daily_pf_runs": 1.0393,
      "daily_pf_hr": 1.2002,
      "pf_weather_delta_runs": 0.0993,
      "pf_weather_delta_hr": 0.2132,
      "wind_venue_sensitivity": 1.0,
      "home_lineup_pf_hr": 2.532,
      "away_lineup_pf_hr": 2.977,
      "lineup_pf_hr_diff": -0.4442,
      "lineup_pf_hr_residual": 1.3322,
      "has_lineups": true,
      "home_lineup_status": "CONFIRMED",
      "away_lineup_status": "CONFIRMED",
      "win_prob_home": 0.555,
      "edge": 0.1036,
      "edge_side": "home",
      "recommendation": "PASS",
      "cgsi_tier": "LOW",
      "consensus_ratio": 1.0,
      "n_specialists_agree": 12
    },
    {
      "game_pk": 824099,
      "home_team": "KC",
      "away_team": "HOU",
      "venue": "Kauffman Stadium",
      "home_pitcher": "Stephen Kolek",
      "away_pitcher": "Spencer Arrighetti",
      "game_time": "2026-06-14T18:10:00Z",
      "temperature_f": 74.2,
      "humidity_pct": 49.0,
      "wind_speed_mph": 11.4,
      "wind_carry_mph": -1.8,
      "air_density_index": 93.8,
      "dome_active": 0,
      "seasonal_pf_runs": 0.99,
      "daily_pf_runs": 1.0149,
      "daily_pf_hr": 1.1117,
      "pf_weather_delta_runs": 0.0249,
      "pf_weather_delta_hr": 0.0722,
      "wind_venue_sensitivity": 1.0,
      "home_lineup_pf_hr": 2.836,
      "away_lineup_pf_hr": 2.526,
      "lineup_pf_hr_diff": 0.3095,
      "lineup_pf_hr_residual": 1.7243,
      "has_lineups": true,
      "home_lineup_status": "CONFIRMED",
      "away_lineup_status": "CONFIRMED",
      "win_prob_home": 0.497,
      "edge": 0.0433,
      "edge_side": "away",
      "recommendation": "PASS",
      "cgsi_tier": "VERY_LOW",
      "consensus_ratio": 0.5,
      "n_specialists_agree": 6
    },
    {
      "game_pk": 823693,
      "home_team": "MIN",
      "away_team": "STL",
      "venue": "Target Field",
      "home_pitcher": "Taj Bradley",
      "away_pitcher": "Michael McGreevy",
      "game_time": "2026-06-14T18:10:00Z",
      "temperature_f": 67.9,
      "humidity_pct": 44.0,
      "wind_speed_mph": 13.7,
      "wind_carry_mph": -9.7,
      "air_density_index": 95.0,
      "dome_active": 0,
      "seasonal_pf_runs": 1.01,
      "daily_pf_runs": 1.0407,
      "daily_pf_hr": 1.0825,
      "pf_weather_delta_runs": 0.0307,
      "pf_weather_delta_hr": 0.022,
      "wind_venue_sensitivity": 1.0,
      "home_lineup_pf_hr": 1.906,
      "away_lineup_pf_hr": 1.683,
      "lineup_pf_hr_diff": 0.2222,
      "lineup_pf_hr_residual": 0.8231,
      "has_lineups": true,
      "home_lineup_status": "CONFIRMED",
      "away_lineup_status": "CONFIRMED",
      "win_prob_home": 0.497,
      "edge": 0.0503,
      "edge_side": "home",
      "recommendation": "PASS",
      "cgsi_tier": "LOW",
      "consensus_ratio": 0.42,
      "n_specialists_agree": 5
    },
    {
      "game_pk": 824586,
      "home_team": "CWS",
      "away_team": "LAD",
      "venue": "Rate Field",
      "home_pitcher": "Bryan Hudson",
      "away_pitcher": "Emmet Sheehan",
      "game_time": "2026-06-14T18:10:00Z",
      "temperature_f": 65.2,
      "humidity_pct": 72.0,
      "wind_speed_mph": 10.2,
      "wind_carry_mph": -9.8,
      "air_density_index": 96.2,
      "dome_active": 0,
      "seasonal_pf_runs": 1.01,
      "daily_pf_runs": 0.9653,
      "daily_pf_hr": 1.0228,
      "pf_weather_delta_runs": -0.0447,
      "pf_weather_delta_hr": -0.0377,
      "wind_venue_sensitivity": 1.0,
      "home_lineup_pf_hr": 1.499,
      "away_lineup_pf_hr": 2.409,
      "lineup_pf_hr_diff": -0.9098,
      "lineup_pf_hr_residual": 0.4763,
      "has_lineups": true,
      "home_lineup_status": "CONFIRMED",
      "away_lineup_status": "CONFIRMED",
      "win_prob_home": 0.463,
      "edge": 0.0927,
      "edge_side": "home",
      "recommendation": "PASS",
      "cgsi_tier": "LOW",
      "consensus_ratio": 0.58,
      "n_specialists_agree": 7
    },
    {
      "game_pk": 823777,
      "home_team": "MIL",
      "away_team": "PHI",
      "venue": "American Family Field",
      "home_pitcher": "Kyle Harrison",
      "away_pitcher": "Cristopher S\u00e1nchez",
      "game_time": "2026-06-14T18:10:00Z",
      "temperature_f": 64.0,
      "humidity_pct": 62.0,
      "wind_speed_mph": 13.4,
      "wind_carry_mph": -3.5,
      "air_density_index": 96.3,
      "dome_active": 0,
      "seasonal_pf_runs": 1.02,
      "daily_pf_runs": 0.9949,
      "daily_pf_hr": 1.031,
      "pf_weather_delta_runs": -0.0251,
      "pf_weather_delta_hr": -0.04,
      "wind_venue_sensitivity": 0.5,
      "home_lineup_pf_hr": 1.992,
      "away_lineup_pf_hr": 2.301,
      "lineup_pf_hr_diff": -0.3094,
      "lineup_pf_hr_residual": 0.9608,
      "has_lineups": true,
      "home_lineup_status": "CONFIRMED",
      "away_lineup_status": "CONFIRMED",
      "win_prob_home": 0.518,
      "edge": 0.1658,
      "edge_side": "home",
      "recommendation": "PASS",
      "cgsi_tier": "LOW",
      "consensus_ratio": 0.75,
      "n_specialists_agree": 9
    },
    {
      "game_pk": 824994,
      "home_team": "OAK",
      "away_team": "COL",
      "venue": "Las Vegas Ballpark",
      "home_pitcher": "Jeffrey Springs",
      "away_pitcher": "Tomoyuki Sugano",
      "game_time": "2026-06-14T19:05:00Z",
      "temperature_f": 85.0,
      "humidity_pct": 53.0,
      "wind_speed_mph": 4.0,
      "wind_carry_mph": 2.0,
      "air_density_index": 94.3,
      "dome_active": 0,
      "seasonal_pf_runs": 0.98,
      "daily_pf_runs": 1.0333,
      "daily_pf_hr": 1.2428,
      "pf_weather_delta_runs": 0.0533,
      "pf_weather_delta_hr": 0.2138,
      "wind_venue_sensitivity": 1.0,
      "home_lineup_pf_hr": 2.676,
      "away_lineup_pf_hr": 2.201,
      "lineup_pf_hr_diff": 0.4748,
      "lineup_pf_hr_residual": 1.4332,
      "has_lineups": true,
      "home_lineup_status": "CONFIRMED",
      "away_lineup_status": "CONFIRMED",
      "win_prob_home": 0.555,
      "edge": 0.0011,
      "edge_side": "home",
      "recommendation": "PASS",
      "cgsi_tier": "LOW",
      "consensus_ratio": 0.83,
      "n_specialists_agree": 10
    },
    {
      "game_pk": 823212,
      "home_team": "SF",
      "away_team": "CHC",
      "venue": "Oracle Park",
      "home_pitcher": "Logan Webb",
      "away_pitcher": "Ryan Rolison",
      "game_time": "2026-06-14T19:10:00Z",
      "temperature_f": 66.6,
      "humidity_pct": 78.0,
      "wind_speed_mph": 7.7,
      "wind_carry_mph": 6.5,
      "air_density_index": 97.9,
      "dome_active": 0,
      "seasonal_pf_runs": 0.93,
      "daily_pf_runs": 0.8983,
      "daily_pf_hr": 0.8228,
      "pf_weather_delta_runs": -0.0317,
      "pf_weather_delta_hr": -0.1537,
      "wind_venue_sensitivity": 1.0,
      "home_lineup_pf_hr": 2.795,
      "away_lineup_pf_hr": 2.783,
      "lineup_pf_hr_diff": 0.0117,
      "lineup_pf_hr_residual": 1.972,
      "has_lineups": true,
      "home_lineup_status": "CONFIRMED",
      "away_lineup_status": "CONFIRMED",
      "win_prob_home": 0.555,
      "edge": 0.0226,
      "edge_side": "home",
      "recommendation": "PASS",
      "cgsi_tier": "LOW",
      "consensus_ratio": 0.83,
      "n_specialists_agree": 10
    },
    {
      "game_pk": 824021,
      "home_team": "LAA",
      "away_team": "TB",
      "venue": "Angel Stadium",
      "home_pitcher": "Grayson Rodriguez",
      "away_pitcher": "Casey Legumina",
      "game_time": "2026-06-14T20:07:00Z",
      "temperature_f": 80.4,
      "humidity_pct": 49.0,
      "wind_speed_mph": 8.3,
      "wind_carry_mph": 7.5,
      "air_density_index": 94.9,
      "dome_active": 0,
      "seasonal_pf_runs": 0.98,
      "daily_pf_runs": 1.0257,
      "daily_pf_hr": 1.2198,
      "pf_weather_delta_runs": 0.0457,
      "pf_weather_delta_hr": 0.1908,
      "wind_venue_sensitivity": 1.0,
      "home_lineup_pf_hr": 2.881,
      "away_lineup_pf_hr": 2.856,
      "lineup_pf_hr_diff": 0.0251,
      "lineup_pf_hr_residual": 1.6617,
      "has_lineups": true,
      "home_lineup_status": "CONFIRMED",
      "away_lineup_status": "CONFIRMED",
      "win_prob_home": 0.497,
      "edge": 0.4124,
      "edge_side": "away",
      "recommendation": "PASS",
      "cgsi_tier": "VERY_LOW",
      "consensus_ratio": 0.25,
      "n_specialists_agree": 3
    },
    {
      "game_pk": 824751,
      "home_team": "BOS",
      "away_team": "TEX",
      "venue": "Fenway Park",
      "home_pitcher": "Connelly Early",
      "away_pitcher": "Nathan Eovaldi",
      "game_time": "2026-06-14T23:20:00Z",
      "temperature_f": 84.5,
      "humidity_pct": 36.0,
      "wind_speed_mph": 13.4,
      "wind_carry_mph": 12.3,
      "air_density_index": 94.7,
      "dome_active": 0,
      "seasonal_pf_runs": 1.03,
      "daily_pf_runs": 1.0405,
      "daily_pf_hr": 1.2452,
      "pf_weather_delta_runs": 0.0105,
      "pf_weather_delta_hr": 0.1637,
      "wind_venue_sensitivity": 1.0,
      "home_lineup_pf_hr": 3.0,
      "away_lineup_pf_hr": 3.0,
      "lineup_pf_hr_diff": 0.0,
      "lineup_pf_hr_residual": 1.7548,
      "has_lineups": true,
      "home_lineup_status": "CONFIRMED",
      "away_lineup_status": "CONFIRMED",
      "win_prob_home": 0.497,
      "edge": 0.0756,
      "edge_side": "home",
      "recommendation": "PASS",
      "cgsi_tier": "LOW",
      "consensus_ratio": 0.25,
      "n_specialists_agree": 3
    },
    {
      "game_pk": 824424,
      "home_team": "CLE",
      "away_team": "DET",
      "venue": "Progressive Field",
      "home_pitcher": "Gavin Williams",
      "away_pitcher": "Casey Mize",
      "game_time": "2026-06-14T17:40:00Z",
      "temperature_f": 84.8,
      "humidity_pct": 53.0,
      "wind_speed_mph": 10.9,
      "wind_carry_mph": 3.4,
      "air_density_index": 92.2,
      "dome_active": 0,
      "seasonal_pf_runs": 0.97,
      "daily_pf_runs": 1.0794,
      "daily_pf_hr": 1.3063,
      "pf_weather_delta_runs": 0.1094,
      "pf_weather_delta_hr": 0.2878,
      "wind_venue_sensitivity": 1.0,
      "home_lineup_pf_hr": null,
      "away_lineup_pf_hr": null,
      "lineup_pf_hr_diff": null,
      "lineup_pf_hr_residual": null,
      "has_lineups": false,
      "home_lineup_status": "CONFIRMED",
      "away_lineup_status": "CONFIRMED",
      "win_prob_home": 0.518,
      "edge": 0.132,
      "edge_side": "home",
      "recommendation": "PASS",
      "cgsi_tier": "LOW",
      "consensus_ratio": 0.83,
      "n_specialists_agree": 10
    }
  ]
}