{
  "date": "2026-05-25",
  "generated_at": "2026-05-25T19:13:37.883761+00:00",
  "predictions_available": true,
  "model_version": "v2.0-approach-c",
  "games": [
    {
      "game_pk": 823380,
      "home_team": "PIT",
      "away_team": "CHC",
      "venue": "PNC Park",
      "home_pitcher": "Carmen Mlodzinski",
      "away_pitcher": "Ben Brown",
      "game_time": "2026-05-25T17:35:00Z",
      "temperature_f": 72.9,
      "humidity_pct": 74.0,
      "wind_speed_mph": 3.4,
      "wind_carry_mph": -2.4,
      "air_density_index": 94.1,
      "dome_active": 0,
      "seasonal_pf_runs": 0.95,
      "daily_pf_runs": 0.9405,
      "daily_pf_hr": 0.9268,
      "pf_weather_delta_runs": -0.0095,
      "pf_weather_delta_hr": -0.0707,
      "wind_venue_sensitivity": 1.0,
      "home_lineup_pf_hr": 2.454,
      "away_lineup_pf_hr": 2.439,
      "lineup_pf_hr_diff": 0.0149,
      "lineup_pf_hr_residual": 1.5269,
      "has_lineups": true,
      "home_lineup_status": "CONFIRMED",
      "away_lineup_status": "CONFIRMED",
      "win_prob_home": null,
      "edge": null,
      "edge_side": null,
      "recommendation": null,
      "cgsi_tier": null,
      "consensus_ratio": null,
      "n_specialists_agree": null
    },
    {
      "game_pk": 824838,
      "home_team": "BAL",
      "away_team": "TB",
      "venue": "Oriole Park at Camden Yards",
      "home_pitcher": "Kyle Bradish",
      "away_pitcher": "Shane McClanahan",
      "game_time": "2026-05-25T17:35:00Z",
      "temperature_f": 70.3,
      "humidity_pct": 94.0,
      "wind_speed_mph": 3.0,
      "wind_carry_mph": 0.9,
      "air_density_index": 96.9,
      "dome_active": 0,
      "seasonal_pf_runs": 1.02,
      "daily_pf_runs": 0.99,
      "daily_pf_hr": 1.0222,
      "pf_weather_delta_runs": -0.03,
      "pf_weather_delta_hr": -0.0488,
      "wind_venue_sensitivity": 1.0,
      "home_lineup_pf_hr": 2.836,
      "away_lineup_pf_hr": 2.541,
      "lineup_pf_hr_diff": 0.2952,
      "lineup_pf_hr_residual": 1.8138,
      "has_lineups": true,
      "home_lineup_status": "CONFIRMED",
      "away_lineup_status": "CONFIRMED",
      "win_prob_home": null,
      "edge": null,
      "edge_side": null,
      "recommendation": null,
      "cgsi_tier": null,
      "consensus_ratio": null,
      "n_specialists_agree": null
    },
    {
      "game_pk": 824598,
      "home_team": "CHW",
      "away_team": "MIN",
      "venue": "Rate Field",
      "home_pitcher": "Anthony Kay",
      "away_pitcher": "Zebby Matthews",
      "game_time": "2026-05-25T18:10:00Z",
      "temperature_f": null,
      "humidity_pct": null,
      "wind_speed_mph": null,
      "wind_carry_mph": null,
      "air_density_index": null,
      "dome_active": 0,
      "seasonal_pf_runs": 1.0,
      "daily_pf_runs": null,
      "daily_pf_hr": null,
      "pf_weather_delta_runs": null,
      "pf_weather_delta_hr": null,
      "wind_venue_sensitivity": null,
      "home_lineup_pf_hr": 0.96,
      "away_lineup_pf_hr": 1.037,
      "lineup_pf_hr_diff": -0.0777,
      "lineup_pf_hr_residual": -0.0403,
      "has_lineups": true,
      "home_lineup_status": "CONFIRMED",
      "away_lineup_status": "CONFIRMED",
      "win_prob_home": null,
      "edge": null,
      "edge_side": null,
      "recommendation": null,
      "cgsi_tier": null,
      "consensus_ratio": null,
      "n_specialists_agree": null
    },
    {
      "game_pk": 823784,
      "home_team": "MIL",
      "away_team": "STL",
      "venue": "American Family Field",
      "home_pitcher": "Jacob Misiorowski",
      "away_pitcher": "Matthew Liberatore",
      "game_time": "2026-05-25T18:10:00Z",
      "temperature_f": 81.9,
      "humidity_pct": 37.0,
      "wind_speed_mph": 6.7,
      "wind_carry_mph": 6.5,
      "air_density_index": 93.1,
      "dome_active": 0,
      "seasonal_pf_runs": 1.02,
      "daily_pf_runs": 1.0638,
      "daily_pf_hr": 1.1798,
      "pf_weather_delta_runs": 0.0438,
      "pf_weather_delta_hr": 0.1088,
      "wind_venue_sensitivity": 0.5,
      "home_lineup_pf_hr": 2.998,
      "away_lineup_pf_hr": 2.535,
      "lineup_pf_hr_diff": 0.4627,
      "lineup_pf_hr_residual": 1.8178,
      "has_lineups": true,
      "home_lineup_status": "CONFIRMED",
      "away_lineup_status": "CONFIRMED",
      "win_prob_home": null,
      "edge": null,
      "edge_side": null,
      "recommendation": null,
      "cgsi_tier": null,
      "consensus_ratio": null,
      "n_specialists_agree": null
    },
    {
      "game_pk": 824107,
      "home_team": "KC",
      "away_team": "NYY",
      "venue": "Kauffman Stadium",
      "home_pitcher": "Michael Wacha",
      "away_pitcher": "Will Warren",
      "game_time": "2026-05-25T19:40:00Z",
      "temperature_f": 84.2,
      "humidity_pct": 38.0,
      "wind_speed_mph": 10.2,
      "wind_carry_mph": 4.3,
      "air_density_index": 92.0,
      "dome_active": 0,
      "seasonal_pf_runs": 0.99,
      "daily_pf_runs": 1.0831,
      "daily_pf_hr": 1.0851,
      "pf_weather_delta_runs": 0.0931,
      "pf_weather_delta_hr": 0.0456,
      "wind_venue_sensitivity": 1.0,
      "home_lineup_pf_hr": 2.969,
      "away_lineup_pf_hr": 2.986,
      "lineup_pf_hr_diff": -0.0169,
      "lineup_pf_hr_residual": 1.8841,
      "has_lineups": true,
      "home_lineup_status": "CONFIRMED",
      "away_lineup_status": "CONFIRMED",
      "win_prob_home": 0.497,
      "edge": 0.0326,
      "edge_side": "home",
      "recommendation": "PASS",
      "cgsi_tier": "LOW",
      "consensus_ratio": 0.42,
      "n_specialists_agree": 5
    },
    {
      "game_pk": 823625,
      "home_team": "NYM",
      "away_team": "CIN",
      "venue": "Citi Field",
      "home_pitcher": "Nolan McLean",
      "away_pitcher": "Nick Lodolo",
      "game_time": "2026-05-25T20:10:00Z",
      "temperature_f": 68.8,
      "humidity_pct": 88.0,
      "wind_speed_mph": 5.1,
      "wind_carry_mph": 5.1,
      "air_density_index": 97.3,
      "dome_active": 0,
      "seasonal_pf_runs": 0.94,
      "daily_pf_runs": 0.9465,
      "daily_pf_hr": 1.0435,
      "pf_weather_delta_runs": 0.0065,
      "pf_weather_delta_hr": 0.0565,
      "wind_venue_sensitivity": 1.0,
      "home_lineup_pf_hr": 2.314,
      "away_lineup_pf_hr": 2.676,
      "lineup_pf_hr_diff": -0.3614,
      "lineup_pf_hr_residual": 1.2707,
      "has_lineups": true,
      "home_lineup_status": "CONFIRMED",
      "away_lineup_status": "CONFIRMED",
      "win_prob_home": 0.603,
      "edge": 0.0516,
      "edge_side": "home",
      "recommendation": "PASS",
      "cgsi_tier": "MEDIUM",
      "consensus_ratio": 0.83,
      "n_specialists_agree": 10
    },
    {
      "game_pk": 823219,
      "home_team": "SF",
      "away_team": "ARI",
      "venue": "Oracle Park",
      "home_pitcher": "Landen Roupp",
      "away_pitcher": "Merrill Kelly",
      "game_time": "2026-05-25T21:05:00Z",
      "temperature_f": 59.9,
      "humidity_pct": 73.0,
      "wind_speed_mph": 13.3,
      "wind_carry_mph": 8.9,
      "air_density_index": 99.3,
      "dome_active": 0,
      "seasonal_pf_runs": 0.93,
      "daily_pf_runs": 0.9169,
      "daily_pf_hr": 0.9177,
      "pf_weather_delta_runs": -0.0131,
      "pf_weather_delta_hr": -0.0588,
      "wind_venue_sensitivity": 1.0,
      "home_lineup_pf_hr": 2.783,
      "away_lineup_pf_hr": 2.31,
      "lineup_pf_hr_diff": 0.4727,
      "lineup_pf_hr_residual": 1.8654,
      "has_lineups": true,
      "home_lineup_status": "CONFIRMED",
      "away_lineup_status": "CONFIRMED",
      "win_prob_home": 0.555,
      "edge": 0.0163,
      "edge_side": "home",
      "recommendation": "PASS",
      "cgsi_tier": "MEDIUM",
      "consensus_ratio": 0.83,
      "n_specialists_agree": 10
    },
    {
      "game_pk": 824437,
      "home_team": "CLE",
      "away_team": "WSH",
      "venue": "Progressive Field",
      "home_pitcher": "Tanner Bibee",
      "away_pitcher": "PJ Poulin",
      "game_time": "2026-05-25T22:10:00Z",
      "temperature_f": 63.0,
      "humidity_pct": 81.0,
      "wind_speed_mph": 7.0,
      "wind_carry_mph": -6.5,
      "air_density_index": 96.3,
      "dome_active": 0,
      "seasonal_pf_runs": 0.97,
      "daily_pf_runs": 0.8981,
      "daily_pf_hr": 0.8175,
      "pf_weather_delta_runs": -0.0719,
      "pf_weather_delta_hr": -0.201,
      "wind_venue_sensitivity": 1.0,
      "home_lineup_pf_hr": 2.006,
      "away_lineup_pf_hr": 1.729,
      "lineup_pf_hr_diff": 0.277,
      "lineup_pf_hr_residual": 1.1888,
      "has_lineups": true,
      "home_lineup_status": "CONFIRMED",
      "away_lineup_status": "CONFIRMED",
      "win_prob_home": 0.62,
      "edge": 0.0026,
      "edge_side": "home",
      "recommendation": "PASS",
      "cgsi_tier": "MEDIUM",
      "consensus_ratio": 1.0,
      "n_specialists_agree": 12
    },
    {
      "game_pk": 823296,
      "home_team": "SD",
      "away_team": "PHI",
      "venue": "Petco Park",
      "home_pitcher": "Griffin Canning",
      "away_pitcher": "Jes\u00fas Luzardo",
      "game_time": "2026-05-25T22:40:00Z",
      "temperature_f": 68.6,
      "humidity_pct": 67.0,
      "wind_speed_mph": 12.2,
      "wind_carry_mph": -11.3,
      "air_density_index": 97.5,
      "dome_active": 0,
      "seasonal_pf_runs": 0.92,
      "daily_pf_runs": 0.8535,
      "daily_pf_hr": 0.8917,
      "pf_weather_delta_runs": -0.0665,
      "pf_weather_delta_hr": -0.0743,
      "wind_venue_sensitivity": 1.0,
      "home_lineup_pf_hr": 1.825,
      "away_lineup_pf_hr": null,
      "lineup_pf_hr_diff": null,
      "lineup_pf_hr_residual": 0.9335,
      "has_lineups": false,
      "home_lineup_status": "CONFIRMED",
      "away_lineup_status": "UNKNOWN",
      "win_prob_home": 0.555,
      "edge": 0.0818,
      "edge_side": "home",
      "recommendation": "PASS",
      "cgsi_tier": "VERY_LOW",
      "consensus_ratio": 0.83,
      "n_specialists_agree": 10
    },
    {
      "game_pk": 822899,
      "home_team": "TEX",
      "away_team": "HOU",
      "venue": "Globe Life Field",
      "home_pitcher": "Kumar Rocker",
      "away_pitcher": "Tatsuya Imai",
      "game_time": "2026-05-25T23:05:00Z",
      "temperature_f": 81.3,
      "humidity_pct": 69.0,
      "wind_speed_mph": 6.3,
      "wind_carry_mph": 2.4,
      "air_density_index": 93.1,
      "dome_active": 0,
      "seasonal_pf_runs": 1.01,
      "daily_pf_runs": 1.0568,
      "daily_pf_hr": 1.0897,
      "pf_weather_delta_runs": 0.0468,
      "pf_weather_delta_hr": 0.0292,
      "wind_venue_sensitivity": 0.5,
      "home_lineup_pf_hr": 2.841,
      "away_lineup_pf_hr": null,
      "lineup_pf_hr_diff": null,
      "lineup_pf_hr_residual": 1.7511,
      "has_lineups": false,
      "home_lineup_status": "CONFIRMED",
      "away_lineup_status": "UNKNOWN",
      "win_prob_home": 0.555,
      "edge": 0.0273,
      "edge_side": "home",
      "recommendation": "PASS",
      "cgsi_tier": "VERY_LOW",
      "consensus_ratio": 1.0,
      "n_specialists_agree": 12
    },
    {
      "game_pk": 822812,
      "home_team": "TOR",
      "away_team": "MIA",
      "venue": "Rogers Centre",
      "home_pitcher": "Trey Yesavage",
      "away_pitcher": "Janson Junk",
      "game_time": "2026-05-25T23:07:00Z",
      "temperature_f": 62.7,
      "humidity_pct": 77.0,
      "wind_speed_mph": 2.4,
      "wind_carry_mph": 2.3,
      "air_density_index": 97.8,
      "dome_active": 0,
      "seasonal_pf_runs": 1.0,
      "daily_pf_runs": 0.9532,
      "daily_pf_hr": 1.079,
      "pf_weather_delta_runs": -0.0468,
      "pf_weather_delta_hr": 0.029,
      "wind_venue_sensitivity": 0.5,
      "home_lineup_pf_hr": null,
      "away_lineup_pf_hr": null,
      "lineup_pf_hr_diff": null,
      "lineup_pf_hr_residual": null,
      "has_lineups": false,
      "home_lineup_status": "UNKNOWN",
      "away_lineup_status": "UNKNOWN",
      "win_prob_home": 0.605,
      "edge": 0.01,
      "edge_side": "home",
      "recommendation": "PASS",
      "cgsi_tier": "LOW",
      "consensus_ratio": 1.0,
      "n_specialists_agree": 12
    },
    {
      "game_pk": 823948,
      "home_team": "LAD",
      "away_team": "COL",
      "venue": "UNIQLO Field at Dodger Stadium",
      "home_pitcher": "Emmet Sheehan",
      "away_pitcher": "Tanner Gordon",
      "game_time": "2026-05-26T01:10:00Z",
      "temperature_f": 66.5,
      "humidity_pct": 60.0,
      "wind_speed_mph": 9.6,
      "wind_carry_mph": -1.7,
      "air_density_index": 96.3,
      "dome_active": 0,
      "seasonal_pf_runs": 0.97,
      "daily_pf_runs": 0.9703,
      "daily_pf_hr": 1.0171,
      "pf_weather_delta_runs": 0.0003,
      "pf_weather_delta_hr": -0.0014,
      "wind_venue_sensitivity": 1.0,
      "home_lineup_pf_hr": null,
      "away_lineup_pf_hr": null,
      "lineup_pf_hr_diff": null,
      "lineup_pf_hr_residual": null,
      "has_lineups": false,
      "home_lineup_status": "UNKNOWN",
      "away_lineup_status": "UNKNOWN",
      "win_prob_home": 0.636,
      "edge": 0.1156,
      "edge_side": "away",
      "recommendation": "PASS",
      "cgsi_tier": "LOW",
      "consensus_ratio": 1.0,
      "n_specialists_agree": 12
    },
    {
      "game_pk": 825005,
      "home_team": "OAK",
      "away_team": "SEA",
      "venue": "Sutter Health Park",
      "home_pitcher": "Aaron Civale",
      "away_pitcher": "Luis Castillo",
      "game_time": "2026-05-26T01:40:00Z",
      "temperature_f": 64.0,
      "humidity_pct": 64.0,
      "wind_speed_mph": 14.2,
      "wind_carry_mph": 8.6,
      "air_density_index": 98.5,
      "dome_active": 0,
      "seasonal_pf_runs": 0.98,
      "daily_pf_runs": 0.9832,
      "daily_pf_hr": 1.0757,
      "pf_weather_delta_runs": 0.0032,
      "pf_weather_delta_hr": 0.0467,
      "wind_venue_sensitivity": 1.0,
      "home_lineup_pf_hr": null,
      "away_lineup_pf_hr": null,
      "lineup_pf_hr_diff": null,
      "lineup_pf_hr_residual": null,
      "has_lineups": false,
      "home_lineup_status": "UNKNOWN",
      "away_lineup_status": "UNKNOWN",
      "win_prob_home": 0.497,
      "edge": 0.011,
      "edge_side": "home",
      "recommendation": "PASS",
      "cgsi_tier": "LOW",
      "consensus_ratio": 0.58,
      "n_specialists_agree": 7
    }
  ]
}