{
  "date": "2026-04-17",
  "generated_at": "2026-04-19T18:47:49.419828+00:00",
  "predictions_available": false,
  "model_version": "v2.0-approach-c",
  "games": [
    {
      "game_pk": 824693,
      "home_team": "CHC",
      "away_team": "NYM",
      "venue": "Wrigley Field",
      "home_pitcher": "Edward Cabrera",
      "away_pitcher": "Kodai Senga",
      "game_time": "2026-04-17T18:20:00Z",
      "temperature_f": 38.9,
      "humidity_pct": 56.0,
      "wind_speed_mph": 9.8,
      "wind_carry_mph": 9.6,
      "air_density_index": 101.6,
      "dome_active": 0,
      "seasonal_pf_runs": 1.05,
      "daily_pf_runs": 0.9863,
      "daily_pf_hr": 0.9007,
      "pf_weather_delta_runs": -0.0637,
      "pf_weather_delta_hr": -0.2018,
      "wind_venue_sensitivity": 1.0,
      "home_lineup_pf_hr": 2.901,
      "away_lineup_pf_hr": 3.0,
      "lineup_pf_hr_diff": -0.099,
      "lineup_pf_hr_residual": 2.0003,
      "has_lineups": true,
      "home_lineup_status": "CONFIRMED",
      "away_lineup_status": "CONFIRMED",
      "win_prob_home": null,
      "edge": null,
      "edge_side": null,
      "recommendation": null,
      "cgsi_tier": null,
      "consensus_ratio": null,
      "n_specialists_agree": null
    },
    {
      "game_pk": 824454,
      "home_team": "CLE",
      "away_team": "BAL",
      "venue": "Progressive Field",
      "home_pitcher": "Tanner Bibee",
      "away_pitcher": "Chris Bassitt",
      "game_time": "2026-04-17T22:10:00Z",
      "temperature_f": 45.7,
      "humidity_pct": 72.0,
      "wind_speed_mph": 15.6,
      "wind_carry_mph": -8.5,
      "air_density_index": 99.9,
      "dome_active": 0,
      "seasonal_pf_runs": 0.97,
      "daily_pf_runs": 0.9217,
      "daily_pf_hr": 0.9028,
      "pf_weather_delta_runs": -0.0483,
      "pf_weather_delta_hr": -0.1157,
      "wind_venue_sensitivity": 1.0,
      "home_lineup_pf_hr": 1.672,
      "away_lineup_pf_hr": 2.488,
      "lineup_pf_hr_diff": -0.8154,
      "lineup_pf_hr_residual": 0.7694,
      "has_lineups": true,
      "home_lineup_status": "CONFIRMED",
      "away_lineup_status": "CONFIRMED",
      "win_prob_home": null,
      "edge": null,
      "edge_side": null,
      "recommendation": null,
      "cgsi_tier": null,
      "consensus_ratio": null,
      "n_specialists_agree": null
    },
    {
      "game_pk": 823476,
      "home_team": "PHI",
      "away_team": "ATL",
      "venue": "Citizens Bank Park",
      "home_pitcher": "Taijuan Walker",
      "away_pitcher": "Mart\u00edn P\u00e9rez",
      "game_time": "2026-04-17T22:40:00Z",
      "temperature_f": 53.3,
      "humidity_pct": 89.0,
      "wind_speed_mph": 6.1,
      "wind_carry_mph": -1.8,
      "air_density_index": 100.5,
      "dome_active": 0,
      "seasonal_pf_runs": 1.06,
      "daily_pf_runs": 0.9963,
      "daily_pf_hr": 0.9721,
      "pf_weather_delta_runs": -0.0637,
      "pf_weather_delta_hr": -0.1409,
      "wind_venue_sensitivity": 1.0,
      "home_lineup_pf_hr": 2.788,
      "away_lineup_pf_hr": 2.794,
      "lineup_pf_hr_diff": -0.0058,
      "lineup_pf_hr_residual": 1.8157,
      "has_lineups": true,
      "home_lineup_status": "CONFIRMED",
      "away_lineup_status": "CONFIRMED",
      "win_prob_home": null,
      "edge": null,
      "edge_side": null,
      "recommendation": null,
      "cgsi_tier": null,
      "consensus_ratio": null,
      "n_specialists_agree": null
    },
    {
      "game_pk": 822752,
      "home_team": "WSH",
      "away_team": "SF",
      "venue": "Nationals Park",
      "home_pitcher": "Zack Littell",
      "away_pitcher": "Logan Webb",
      "game_time": "2026-04-17T22:45:00Z",
      "temperature_f": 64.4,
      "humidity_pct": 79.0,
      "wind_speed_mph": 8.0,
      "wind_carry_mph": -4.0,
      "air_density_index": 98.3,
      "dome_active": 0,
      "seasonal_pf_runs": 0.99,
      "daily_pf_runs": 0.9136,
      "daily_pf_hr": 0.9199,
      "pf_weather_delta_runs": -0.0764,
      "pf_weather_delta_hr": -0.1196,
      "wind_venue_sensitivity": 1.0,
      "home_lineup_pf_hr": 2.008,
      "away_lineup_pf_hr": 2.168,
      "lineup_pf_hr_diff": -0.1599,
      "lineup_pf_hr_residual": 1.0884,
      "has_lineups": true,
      "home_lineup_status": "CONFIRMED",
      "away_lineup_status": "CONFIRMED",
      "win_prob_home": null,
      "edge": null,
      "edge_side": null,
      "recommendation": null,
      "cgsi_tier": null,
      "consensus_ratio": null,
      "n_specialists_agree": null
    },
    {
      "game_pk": 823397,
      "home_team": "PIT",
      "away_team": "TB",
      "venue": "PNC Park",
      "home_pitcher": "Bubba Chandler",
      "away_pitcher": "Nick Martinez",
      "game_time": "2026-04-17T22:45:00Z",
      "temperature_f": 54.7,
      "humidity_pct": 84.0,
      "wind_speed_mph": 7.5,
      "wind_carry_mph": 1.2,
      "air_density_index": 97.7,
      "dome_active": 0,
      "seasonal_pf_runs": 0.95,
      "daily_pf_runs": 0.8911,
      "daily_pf_hr": 0.8242,
      "pf_weather_delta_runs": -0.0589,
      "pf_weather_delta_hr": -0.1733,
      "wind_venue_sensitivity": 1.0,
      "home_lineup_pf_hr": 2.777,
      "away_lineup_pf_hr": 2.685,
      "lineup_pf_hr_diff": 0.0925,
      "lineup_pf_hr_residual": 1.9529,
      "has_lineups": true,
      "home_lineup_status": "CONFIRMED",
      "away_lineup_status": "CONFIRMED",
      "win_prob_home": null,
      "edge": null,
      "edge_side": null,
      "recommendation": null,
      "cgsi_tier": null,
      "consensus_ratio": null,
      "n_specialists_agree": null
    },
    {
      "game_pk": 823559,
      "home_team": "NYY",
      "away_team": "KC",
      "venue": "Yankee Stadium",
      "home_pitcher": "Cam Schlittler",
      "away_pitcher": "Michael Wacha",
      "game_time": "2026-04-17T23:05:00Z",
      "temperature_f": 48.9,
      "humidity_pct": 95.0,
      "wind_speed_mph": 6.2,
      "wind_carry_mph": -1.0,
      "air_density_index": 101.5,
      "dome_active": 0,
      "seasonal_pf_runs": 1.05,
      "daily_pf_runs": 0.9842,
      "daily_pf_hr": 1.081,
      "pf_weather_delta_runs": -0.0658,
      "pf_weather_delta_hr": -0.0215,
      "wind_venue_sensitivity": 1.0,
      "home_lineup_pf_hr": 2.865,
      "away_lineup_pf_hr": 2.764,
      "lineup_pf_hr_diff": 0.1004,
      "lineup_pf_hr_residual": 1.7836,
      "has_lineups": true,
      "home_lineup_status": "CONFIRMED",
      "away_lineup_status": "CONFIRMED",
      "win_prob_home": null,
      "edge": null,
      "edge_side": null,
      "recommendation": null,
      "cgsi_tier": null,
      "consensus_ratio": null,
      "n_specialists_agree": null
    },
    {
      "game_pk": 823883,
      "home_team": "MIA",
      "away_team": "MIL",
      "venue": "loanDepot park",
      "home_pitcher": "Janson Junk",
      "away_pitcher": "Coleman Crow",
      "game_time": "2026-04-17T23:10:00Z",
      "temperature_f": 74.2,
      "humidity_pct": 84.0,
      "wind_speed_mph": 7.0,
      "wind_carry_mph": -0.6,
      "air_density_index": 96.2,
      "dome_active": 0,
      "seasonal_pf_runs": 0.93,
      "daily_pf_runs": 0.8717,
      "daily_pf_hr": 0.792,
      "pf_weather_delta_runs": -0.0583,
      "pf_weather_delta_hr": -0.1845,
      "wind_venue_sensitivity": 0.5,
      "home_lineup_pf_hr": 2.715,
      "away_lineup_pf_hr": 2.055,
      "lineup_pf_hr_diff": 0.6599,
      "lineup_pf_hr_residual": 1.9228,
      "has_lineups": true,
      "home_lineup_status": "CONFIRMED",
      "away_lineup_status": "CONFIRMED",
      "win_prob_home": null,
      "edge": null,
      "edge_side": null,
      "recommendation": null,
      "cgsi_tier": null,
      "consensus_ratio": null,
      "n_specialists_agree": null
    },
    {
      "game_pk": 824778,
      "home_team": "BOS",
      "away_team": "DET",
      "venue": "Fenway Park",
      "home_pitcher": "Ranger Suarez",
      "away_pitcher": "Casey Mize",
      "game_time": "2026-04-17T23:15:00Z",
      "temperature_f": 43.8,
      "humidity_pct": 97.0,
      "wind_speed_mph": 3.5,
      "wind_carry_mph": -3.4,
      "air_density_index": 102.6,
      "dome_active": 0,
      "seasonal_pf_runs": 1.03,
      "daily_pf_runs": 0.9517,
      "daily_pf_hr": 1.0174,
      "pf_weather_delta_runs": -0.0783,
      "pf_weather_delta_hr": -0.0641,
      "wind_venue_sensitivity": 1.0,
      "home_lineup_pf_hr": 2.713,
      "away_lineup_pf_hr": 2.411,
      "lineup_pf_hr_diff": 0.3021,
      "lineup_pf_hr_residual": 1.6956,
      "has_lineups": true,
      "home_lineup_status": "CONFIRMED",
      "away_lineup_status": "CONFIRMED",
      "win_prob_home": null,
      "edge": null,
      "edge_side": null,
      "recommendation": null,
      "cgsi_tier": null,
      "consensus_ratio": null,
      "n_specialists_agree": null
    },
    {
      "game_pk": 824207,
      "home_team": "HOU",
      "away_team": "STL",
      "venue": "Daikin Park",
      "home_pitcher": "Peter Lambert",
      "away_pitcher": "Kyle Leahy",
      "game_time": "2026-04-18T00:10:00Z",
      "temperature_f": 58.1,
      "humidity_pct": 93.0,
      "wind_speed_mph": 11.2,
      "wind_carry_mph": -3.5,
      "air_density_index": 99.5,
      "dome_active": 0,
      "seasonal_pf_runs": 1.04,
      "daily_pf_runs": 0.9725,
      "daily_pf_hr": 1.1252,
      "pf_weather_delta_runs": -0.0675,
      "pf_weather_delta_hr": 0.0332,
      "wind_venue_sensitivity": 0.5,
      "home_lineup_pf_hr": 2.411,
      "away_lineup_pf_hr": 2.106,
      "lineup_pf_hr_diff": 0.3048,
      "lineup_pf_hr_residual": 1.2855,
      "has_lineups": true,
      "home_lineup_status": "CONFIRMED",
      "away_lineup_status": "CONFIRMED",
      "win_prob_home": null,
      "edge": null,
      "edge_side": null,
      "recommendation": null,
      "cgsi_tier": null,
      "consensus_ratio": null,
      "n_specialists_agree": null
    },
    {
      "game_pk": 823720,
      "home_team": "MIN",
      "away_team": "CIN",
      "venue": "Target Field",
      "home_pitcher": "Joe Ryan",
      "away_pitcher": "Brandon Williamson",
      "game_time": "2026-04-18T00:10:00Z",
      "temperature_f": 38.5,
      "humidity_pct": 39.0,
      "wind_speed_mph": 2.9,
      "wind_carry_mph": 1.4,
      "air_density_index": 100.9,
      "dome_active": 0,
      "seasonal_pf_runs": 1.01,
      "daily_pf_runs": 0.9904,
      "daily_pf_hr": 0.8517,
      "pf_weather_delta_runs": -0.0196,
      "pf_weather_delta_hr": -0.2088,
      "wind_venue_sensitivity": 1.0,
      "home_lineup_pf_hr": 2.528,
      "away_lineup_pf_hr": 2.593,
      "lineup_pf_hr_diff": -0.0647,
      "lineup_pf_hr_residual": 1.6766,
      "has_lineups": true,
      "home_lineup_status": "CONFIRMED",
      "away_lineup_status": "CONFIRMED",
      "win_prob_home": null,
      "edge": null,
      "edge_side": null,
      "recommendation": null,
      "cgsi_tier": null,
      "consensus_ratio": null,
      "n_specialists_agree": null
    },
    {
      "game_pk": 824373,
      "home_team": "COL",
      "away_team": "LAD",
      "venue": "Coors Field",
      "home_pitcher": "Tomoyuki Sugano",
      "away_pitcher": "Tyler Glasnow",
      "game_time": "2026-04-18T00:40:00Z",
      "temperature_f": 44.8,
      "humidity_pct": 22.0,
      "wind_speed_mph": 1.6,
      "wind_carry_mph": 1.2,
      "air_density_index": 84.9,
      "dome_active": 0,
      "seasonal_pf_runs": 1.261,
      "daily_pf_runs": 1.3371,
      "daily_pf_hr": 1.2172,
      "pf_weather_delta_runs": 0.0761,
      "pf_weather_delta_hr": -0.1068,
      "wind_venue_sensitivity": 1.0,
      "home_lineup_pf_hr": 2.331,
      "away_lineup_pf_hr": 2.839,
      "lineup_pf_hr_diff": -0.5077,
      "lineup_pf_hr_residual": 1.1139,
      "has_lineups": true,
      "home_lineup_status": "CONFIRMED",
      "away_lineup_status": "CONFIRMED",
      "win_prob_home": null,
      "edge": null,
      "edge_side": null,
      "recommendation": null,
      "cgsi_tier": null,
      "consensus_ratio": null,
      "n_specialists_agree": null
    },
    {
      "game_pk": 824048,
      "home_team": "LAA",
      "away_team": "SD",
      "venue": "Angel Stadium",
      "home_pitcher": "Jos\u00e9 Soriano",
      "away_pitcher": "Matt Waldron",
      "game_time": "2026-04-18T01:38:00Z",
      "temperature_f": 65.9,
      "humidity_pct": 69.0,
      "wind_speed_mph": 7.1,
      "wind_carry_mph": 6.0,
      "air_density_index": 97.6,
      "dome_active": 0,
      "seasonal_pf_runs": 0.98,
      "daily_pf_runs": 0.9567,
      "daily_pf_hr": 1.0197,
      "pf_weather_delta_runs": -0.0233,
      "pf_weather_delta_hr": -0.0093,
      "wind_venue_sensitivity": 1.0,
      "home_lineup_pf_hr": 3.0,
      "away_lineup_pf_hr": 3.0,
      "lineup_pf_hr_diff": 0.0,
      "lineup_pf_hr_residual": 1.9803,
      "has_lineups": true,
      "home_lineup_status": "CONFIRMED",
      "away_lineup_status": "CONFIRMED",
      "win_prob_home": null,
      "edge": null,
      "edge_side": null,
      "recommendation": null,
      "cgsi_tier": null,
      "consensus_ratio": null,
      "n_specialists_agree": null
    },
    {
      "game_pk": 823152,
      "home_team": "SEA",
      "away_team": "TEX",
      "venue": "T-Mobile Park",
      "home_pitcher": "Logan Gilbert",
      "away_pitcher": "Jacob deGrom",
      "game_time": "2026-04-18T01:40:00Z",
      "temperature_f": 59.6,
      "humidity_pct": 45.0,
      "wind_speed_mph": 3.4,
      "wind_carry_mph": -2.7,
      "air_density_index": 99.5,
      "dome_active": 0,
      "seasonal_pf_runs": 0.94,
      "daily_pf_runs": 0.9012,
      "daily_pf_hr": 0.962,
      "pf_weather_delta_runs": -0.0388,
      "pf_weather_delta_hr": -0.025,
      "wind_venue_sensitivity": 0.5,
      "home_lineup_pf_hr": 2.18,
      "away_lineup_pf_hr": 2.321,
      "lineup_pf_hr_diff": -0.1409,
      "lineup_pf_hr_residual": 1.218,
      "has_lineups": true,
      "home_lineup_status": "CONFIRMED",
      "away_lineup_status": "CONFIRMED",
      "win_prob_home": null,
      "edge": null,
      "edge_side": null,
      "recommendation": null,
      "cgsi_tier": null,
      "consensus_ratio": null,
      "n_specialists_agree": null
    },
    {
      "game_pk": 825101,
      "home_team": "ARI",
      "away_team": "TOR",
      "venue": "Chase Field",
      "home_pitcher": "Michael Soroka",
      "away_pitcher": "Braydon Fisher",
      "game_time": "2026-04-18T01:40:00Z",
      "temperature_f": 79.6,
      "humidity_pct": 6.0,
      "wind_speed_mph": 3.0,
      "wind_carry_mph": -2.7,
      "air_density_index": 92.3,
      "dome_active": 0,
      "seasonal_pf_runs": 1.049,
      "daily_pf_runs": 1.07,
      "daily_pf_hr": 1.0399,
      "pf_weather_delta_runs": 0.021,
      "pf_weather_delta_hr": -0.0615,
      "wind_venue_sensitivity": 0.5,
      "home_lineup_pf_hr": 2.216,
      "away_lineup_pf_hr": 1.893,
      "lineup_pf_hr_diff": 0.3224,
      "lineup_pf_hr_residual": 1.1757,
      "has_lineups": true,
      "home_lineup_status": "CONFIRMED",
      "away_lineup_status": "CONFIRMED",
      "win_prob_home": null,
      "edge": null,
      "edge_side": null,
      "recommendation": null,
      "cgsi_tier": null,
      "consensus_ratio": null,
      "n_specialists_agree": null
    },
    {
      "game_pk": 825019,
      "home_team": "OAK",
      "away_team": "CWS",
      "venue": "Sutter Health Park",
      "home_pitcher": "Aaron Civale",
      "away_pitcher": "Davis Martin",
      "game_time": "2026-04-18T01:40:00Z",
      "temperature_f": 65.1,
      "humidity_pct": 38.0,
      "wind_speed_mph": 2.0,
      "wind_carry_mph": 0.3,
      "air_density_index": 98.4,
      "dome_active": 0,
      "seasonal_pf_runs": 0.98,
      "daily_pf_runs": 1.0301,
      "daily_pf_hr": 0.9631,
      "pf_weather_delta_runs": 0.0501,
      "pf_weather_delta_hr": -0.0659,
      "wind_venue_sensitivity": 1.0,
      "home_lineup_pf_hr": 2.548,
      "away_lineup_pf_hr": 2.303,
      "lineup_pf_hr_diff": 0.2456,
      "lineup_pf_hr_residual": 1.585,
      "has_lineups": true,
      "home_lineup_status": "CONFIRMED",
      "away_lineup_status": "CONFIRMED",
      "win_prob_home": null,
      "edge": null,
      "edge_side": null,
      "recommendation": null,
      "cgsi_tier": null,
      "consensus_ratio": null,
      "n_specialists_agree": null
    }
  ]
}