{
  "date": "2026-05-02",
  "generated_at": "2026-05-01T00:24:04.232154+00:00",
  "predictions_available": false,
  "model_version": "v2.0-approach-c",
  "games": [
    {
      "game_pk": 823554,
      "home_team": "NYY",
      "away_team": "BAL",
      "venue": "Yankee Stadium",
      "home_pitcher": "Ryan Weathers",
      "away_pitcher": "",
      "game_time": "2026-05-02T17:35:00Z",
      "temperature_f": 48.2,
      "humidity_pct": 78.0,
      "wind_speed_mph": 6.3,
      "wind_carry_mph": 4.7,
      "air_density_index": 101.7,
      "dome_active": 0,
      "seasonal_pf_runs": 1.05,
      "daily_pf_runs": 1.0071,
      "daily_pf_hr": 0.9611,
      "pf_weather_delta_runs": -0.0429,
      "pf_weather_delta_hr": -0.1414,
      "wind_venue_sensitivity": 1.0,
      "home_lineup_pf_hr": null,
      "away_lineup_pf_hr": null,
      "lineup_pf_hr_diff": null,
      "lineup_pf_hr_residual": null,
      "has_lineups": false,
      "home_lineup_status": "UNKNOWN",
      "away_lineup_status": "UNKNOWN",
      "win_prob_home": null,
      "edge": null,
      "edge_side": null,
      "recommendation": null,
      "cgsi_tier": null,
      "consensus_ratio": null,
      "n_specialists_agree": null
    },
    {
      "game_pk": 823715,
      "home_team": "MIN",
      "away_team": "TOR",
      "venue": "Target Field",
      "home_pitcher": "Connor Prielipp",
      "away_pitcher": "Dylan Cease",
      "game_time": "2026-05-02T18:10:00Z",
      "temperature_f": 39.9,
      "humidity_pct": 60.0,
      "wind_speed_mph": 4.4,
      "wind_carry_mph": 3.2,
      "air_density_index": 100.5,
      "dome_active": 0,
      "seasonal_pf_runs": 1.01,
      "daily_pf_runs": 0.9732,
      "daily_pf_hr": 0.8756,
      "pf_weather_delta_runs": -0.0368,
      "pf_weather_delta_hr": -0.1849,
      "wind_venue_sensitivity": 1.0,
      "home_lineup_pf_hr": null,
      "away_lineup_pf_hr": null,
      "lineup_pf_hr_diff": null,
      "lineup_pf_hr_residual": null,
      "has_lineups": false,
      "home_lineup_status": "UNKNOWN",
      "away_lineup_status": "UNKNOWN",
      "win_prob_home": null,
      "edge": null,
      "edge_side": null,
      "recommendation": null,
      "cgsi_tier": null,
      "consensus_ratio": null,
      "n_specialists_agree": null
    },
    {
      "game_pk": 824685,
      "home_team": "CHC",
      "away_team": "ARI",
      "venue": "Wrigley Field",
      "home_pitcher": "Shota Imanaga",
      "away_pitcher": "Ryne Nelson",
      "game_time": "2026-05-02T18:20:00Z",
      "temperature_f": 37.4,
      "humidity_pct": 77.0,
      "wind_speed_mph": 0.4,
      "wind_carry_mph": -0.2,
      "air_density_index": 101.9,
      "dome_active": 0,
      "seasonal_pf_runs": 1.05,
      "daily_pf_runs": 0.9794,
      "daily_pf_hr": 0.8691,
      "pf_weather_delta_runs": -0.0706,
      "pf_weather_delta_hr": -0.2334,
      "wind_venue_sensitivity": 1.0,
      "home_lineup_pf_hr": null,
      "away_lineup_pf_hr": null,
      "lineup_pf_hr_diff": null,
      "lineup_pf_hr_residual": null,
      "has_lineups": false,
      "home_lineup_status": "UNKNOWN",
      "away_lineup_status": "UNKNOWN",
      "win_prob_home": null,
      "edge": null,
      "edge_side": null,
      "recommendation": null,
      "cgsi_tier": null,
      "consensus_ratio": null,
      "n_specialists_agree": null
    },
    {
      "game_pk": 825014,
      "home_team": "OAK",
      "away_team": "CLE",
      "venue": "Sutter Health Park",
      "home_pitcher": "Jacob Lopez",
      "away_pitcher": "Slade Cecconi",
      "game_time": "2026-05-02T20:05:00Z",
      "temperature_f": 67.7,
      "humidity_pct": 60.0,
      "wind_speed_mph": 8.6,
      "wind_carry_mph": 6.4,
      "air_density_index": 97.7,
      "dome_active": 0,
      "seasonal_pf_runs": 0.98,
      "daily_pf_runs": 0.9691,
      "daily_pf_hr": 1.0877,
      "pf_weather_delta_runs": -0.0109,
      "pf_weather_delta_hr": 0.0587,
      "wind_venue_sensitivity": 1.0,
      "home_lineup_pf_hr": null,
      "away_lineup_pf_hr": null,
      "lineup_pf_hr_diff": null,
      "lineup_pf_hr_residual": null,
      "has_lineups": false,
      "home_lineup_status": "UNKNOWN",
      "away_lineup_status": "UNKNOWN",
      "win_prob_home": null,
      "edge": null,
      "edge_side": null,
      "recommendation": null,
      "cgsi_tier": null,
      "consensus_ratio": null,
      "n_specialists_agree": null
    },
    {
      "game_pk": 823388,
      "home_team": "PIT",
      "away_team": "CIN",
      "venue": "PNC Park",
      "home_pitcher": "Carmen Mlodzinski",
      "away_pitcher": "Rhett Lowder",
      "game_time": "2026-05-02T20:05:00Z",
      "temperature_f": 39.0,
      "humidity_pct": 90.0,
      "wind_speed_mph": 3.9,
      "wind_carry_mph": 2.8,
      "air_density_index": 101.0,
      "dome_active": 0,
      "seasonal_pf_runs": 0.95,
      "daily_pf_runs": 0.8885,
      "daily_pf_hr": 0.874,
      "pf_weather_delta_runs": -0.0615,
      "pf_weather_delta_hr": -0.1235,
      "wind_venue_sensitivity": 1.0,
      "home_lineup_pf_hr": null,
      "away_lineup_pf_hr": null,
      "lineup_pf_hr_diff": null,
      "lineup_pf_hr_residual": null,
      "has_lineups": false,
      "home_lineup_status": "UNKNOWN",
      "away_lineup_status": "UNKNOWN",
      "win_prob_home": null,
      "edge": null,
      "edge_side": null,
      "recommendation": null,
      "cgsi_tier": null,
      "consensus_ratio": null,
      "n_specialists_agree": null
    },
    {
      "game_pk": 822746,
      "home_team": "WSH",
      "away_team": "MIL",
      "venue": "Nationals Park",
      "home_pitcher": "Foster Griffin",
      "away_pitcher": "Kyle Harrison",
      "game_time": "2026-05-02T20:05:00Z",
      "temperature_f": 57.3,
      "humidity_pct": 49.0,
      "wind_speed_mph": 3.6,
      "wind_carry_mph": 1.4,
      "air_density_index": 99.9,
      "dome_active": 0,
      "seasonal_pf_runs": 0.99,
      "daily_pf_runs": 0.9645,
      "daily_pf_hr": 0.9864,
      "pf_weather_delta_runs": -0.0255,
      "pf_weather_delta_hr": -0.0531,
      "wind_venue_sensitivity": 1.0,
      "home_lineup_pf_hr": null,
      "away_lineup_pf_hr": null,
      "lineup_pf_hr_diff": null,
      "lineup_pf_hr_residual": null,
      "has_lineups": false,
      "home_lineup_status": "UNKNOWN",
      "away_lineup_status": "UNKNOWN",
      "win_prob_home": null,
      "edge": null,
      "edge_side": null,
      "recommendation": null,
      "cgsi_tier": null,
      "consensus_ratio": null,
      "n_specialists_agree": null
    },
    {
      "game_pk": 824771,
      "home_team": "BOS",
      "away_team": "HOU",
      "venue": "Fenway Park",
      "home_pitcher": "Connelly Early",
      "away_pitcher": "Spencer Arrighetti",
      "game_time": "2026-05-02T20:10:00Z",
      "temperature_f": 47.9,
      "humidity_pct": 42.0,
      "wind_speed_mph": 4.4,
      "wind_carry_mph": 4.2,
      "air_density_index": 101.9,
      "dome_active": 0,
      "seasonal_pf_runs": 1.03,
      "daily_pf_runs": 1.011,
      "daily_pf_hr": 0.8544,
      "pf_weather_delta_runs": -0.019,
      "pf_weather_delta_hr": -0.2271,
      "wind_venue_sensitivity": 1.0,
      "home_lineup_pf_hr": null,
      "away_lineup_pf_hr": null,
      "lineup_pf_hr_diff": null,
      "lineup_pf_hr_residual": null,
      "has_lineups": false,
      "home_lineup_status": "UNKNOWN",
      "away_lineup_status": "UNKNOWN",
      "win_prob_home": null,
      "edge": null,
      "edge_side": null,
      "recommendation": null,
      "cgsi_tier": null,
      "consensus_ratio": null,
      "n_specialists_agree": null
    },
    {
      "game_pk": 823876,
      "home_team": "MIA",
      "away_team": "PHI",
      "venue": "loanDepot park",
      "home_pitcher": "Max Meyer",
      "away_pitcher": "",
      "game_time": "2026-05-02T20:10:00Z",
      "temperature_f": 74.6,
      "humidity_pct": 77.0,
      "wind_speed_mph": 4.3,
      "wind_carry_mph": 3.4,
      "air_density_index": 96.2,
      "dome_active": 0,
      "seasonal_pf_runs": 0.93,
      "daily_pf_runs": 0.8955,
      "daily_pf_hr": 0.8982,
      "pf_weather_delta_runs": -0.0345,
      "pf_weather_delta_hr": -0.0783,
      "wind_venue_sensitivity": 0.5,
      "home_lineup_pf_hr": null,
      "away_lineup_pf_hr": null,
      "lineup_pf_hr_diff": null,
      "lineup_pf_hr_residual": null,
      "has_lineups": false,
      "home_lineup_status": "UNKNOWN",
      "away_lineup_status": "UNKNOWN",
      "win_prob_home": null,
      "edge": null,
      "edge_side": null,
      "recommendation": null,
      "cgsi_tier": null,
      "consensus_ratio": null,
      "n_specialists_agree": null
    },
    {
      "game_pk": 822988,
      "home_team": "TB",
      "away_team": "SF",
      "venue": "Tropicana Field",
      "home_pitcher": "",
      "away_pitcher": "Landen Roupp",
      "game_time": "2026-05-02T22:10:00Z",
      "temperature_f": 72.0,
      "humidity_pct": 50.0,
      "wind_speed_mph": 0.0,
      "wind_carry_mph": 0.0,
      "air_density_index": 96.9,
      "dome_active": 1,
      "seasonal_pf_runs": 0.91,
      "daily_pf_runs": 0.91,
      "daily_pf_hr": 0.9555,
      "pf_weather_delta_runs": 0.0,
      "pf_weather_delta_hr": -0.0,
      "wind_venue_sensitivity": 0.0,
      "home_lineup_pf_hr": null,
      "away_lineup_pf_hr": null,
      "lineup_pf_hr_diff": null,
      "lineup_pf_hr_residual": null,
      "has_lineups": false,
      "home_lineup_status": "UNKNOWN",
      "away_lineup_status": "UNKNOWN",
      "win_prob_home": null,
      "edge": null,
      "edge_side": null,
      "recommendation": null,
      "cgsi_tier": null,
      "consensus_ratio": null,
      "n_specialists_agree": null
    },
    {
      "game_pk": 823067,
      "home_team": "STL",
      "away_team": "LAD",
      "venue": "Busch Stadium",
      "home_pitcher": "Michael McGreevy",
      "away_pitcher": "Roki Sasaki",
      "game_time": "2026-05-02T23:15:00Z",
      "temperature_f": 49.9,
      "humidity_pct": 50.0,
      "wind_speed_mph": 4.5,
      "wind_carry_mph": 4.0,
      "air_density_index": 99.9,
      "dome_active": 0,
      "seasonal_pf_runs": 0.97,
      "daily_pf_runs": 0.9344,
      "daily_pf_hr": 0.877,
      "pf_weather_delta_runs": -0.0356,
      "pf_weather_delta_hr": -0.1415,
      "wind_venue_sensitivity": 1.0,
      "home_lineup_pf_hr": null,
      "away_lineup_pf_hr": null,
      "lineup_pf_hr_diff": null,
      "lineup_pf_hr_residual": null,
      "has_lineups": false,
      "home_lineup_status": "UNKNOWN",
      "away_lineup_status": "UNKNOWN",
      "win_prob_home": null,
      "edge": null,
      "edge_side": null,
      "recommendation": null,
      "cgsi_tier": null,
      "consensus_ratio": null,
      "n_specialists_agree": null
    },
    {
      "game_pk": 824284,
      "home_team": "DET",
      "away_team": "TEX",
      "venue": "Comerica Park",
      "home_pitcher": "Keider Montero",
      "away_pitcher": "Kumar Rocker",
      "game_time": "2026-05-02T23:15:00Z",
      "temperature_f": 40.0,
      "humidity_pct": 92.0,
      "wind_speed_mph": 4.6,
      "wind_carry_mph": 1.3,
      "air_density_index": 101.3,
      "dome_active": 0,
      "seasonal_pf_runs": 0.96,
      "daily_pf_runs": 0.9033,
      "daily_pf_hr": 0.8415,
      "pf_weather_delta_runs": -0.0567,
      "pf_weather_delta_hr": -0.1665,
      "wind_venue_sensitivity": 1.0,
      "home_lineup_pf_hr": null,
      "away_lineup_pf_hr": null,
      "lineup_pf_hr_diff": null,
      "lineup_pf_hr_residual": null,
      "has_lineups": false,
      "home_lineup_status": "UNKNOWN",
      "away_lineup_status": "UNKNOWN",
      "win_prob_home": null,
      "edge": null,
      "edge_side": null,
      "recommendation": null,
      "cgsi_tier": null,
      "consensus_ratio": null,
      "n_specialists_agree": null
    },
    {
      "game_pk": 824365,
      "home_team": "COL",
      "away_team": "ATL",
      "venue": "Coors Field",
      "home_pitcher": "",
      "away_pitcher": "Chris Sale",
      "game_time": "2026-05-03T00:10:00Z",
      "temperature_f": 50.6,
      "humidity_pct": 14.0,
      "wind_speed_mph": 5.4,
      "wind_carry_mph": -0.2,
      "air_density_index": 83.9,
      "dome_active": 0,
      "seasonal_pf_runs": 1.261,
      "daily_pf_runs": 1.322,
      "daily_pf_hr": 1.3566,
      "pf_weather_delta_runs": 0.061,
      "pf_weather_delta_hr": 0.0326,
      "wind_venue_sensitivity": 1.0,
      "home_lineup_pf_hr": null,
      "away_lineup_pf_hr": null,
      "lineup_pf_hr_diff": null,
      "lineup_pf_hr_residual": null,
      "has_lineups": false,
      "home_lineup_status": "UNKNOWN",
      "away_lineup_status": "UNKNOWN",
      "win_prob_home": null,
      "edge": null,
      "edge_side": null,
      "recommendation": null,
      "cgsi_tier": null,
      "consensus_ratio": null,
      "n_specialists_agree": null
    },
    {
      "game_pk": 823308,
      "home_team": "SD",
      "away_team": "CWS",
      "venue": "Petco Park",
      "home_pitcher": "Michael King",
      "away_pitcher": "Sean Burke",
      "game_time": "2026-05-03T00:40:00Z",
      "temperature_f": 59.8,
      "humidity_pct": 93.0,
      "wind_speed_mph": 3.4,
      "wind_carry_mph": -3.3,
      "air_density_index": 99.2,
      "dome_active": 0,
      "seasonal_pf_runs": 0.92,
      "daily_pf_runs": 0.8663,
      "daily_pf_hr": 0.8621,
      "pf_weather_delta_runs": -0.0537,
      "pf_weather_delta_hr": -0.1039,
      "wind_venue_sensitivity": 1.0,
      "home_lineup_pf_hr": null,
      "away_lineup_pf_hr": null,
      "lineup_pf_hr_diff": null,
      "lineup_pf_hr_residual": null,
      "has_lineups": false,
      "home_lineup_status": "UNKNOWN",
      "away_lineup_status": "UNKNOWN",
      "win_prob_home": null,
      "edge": null,
      "edge_side": null,
      "recommendation": null,
      "cgsi_tier": null,
      "consensus_ratio": null,
      "n_specialists_agree": null
    },
    {
      "game_pk": 824042,
      "home_team": "LAA",
      "away_team": "NYM",
      "venue": "Angel Stadium",
      "home_pitcher": "Reid Detmers",
      "away_pitcher": "Nolan McLean",
      "game_time": "2026-05-03T01:38:00Z",
      "temperature_f": 60.8,
      "humidity_pct": 86.0,
      "wind_speed_mph": 5.6,
      "wind_carry_mph": 5.4,
      "air_density_index": 98.5,
      "dome_active": 0,
      "seasonal_pf_runs": 0.98,
      "daily_pf_runs": 0.9374,
      "daily_pf_hr": 0.9457,
      "pf_weather_delta_runs": -0.0426,
      "pf_weather_delta_hr": -0.0833,
      "wind_venue_sensitivity": 1.0,
      "home_lineup_pf_hr": null,
      "away_lineup_pf_hr": null,
      "lineup_pf_hr_diff": null,
      "lineup_pf_hr_residual": null,
      "has_lineups": false,
      "home_lineup_status": "UNKNOWN",
      "away_lineup_status": "UNKNOWN",
      "win_prob_home": null,
      "edge": null,
      "edge_side": null,
      "recommendation": null,
      "cgsi_tier": null,
      "consensus_ratio": null,
      "n_specialists_agree": null
    },
    {
      "game_pk": 823144,
      "home_team": "SEA",
      "away_team": "KC",
      "venue": "T-Mobile Park",
      "home_pitcher": "Emerson Hancock",
      "away_pitcher": "Seth Lugo",
      "game_time": "2026-05-03T01:40:00Z",
      "temperature_f": 60.3,
      "humidity_pct": 61.0,
      "wind_speed_mph": 4.5,
      "wind_carry_mph": -3.6,
      "air_density_index": 99.3,
      "dome_active": 0,
      "seasonal_pf_runs": 0.94,
      "daily_pf_runs": 0.8737,
      "daily_pf_hr": 0.9327,
      "pf_weather_delta_runs": -0.0663,
      "pf_weather_delta_hr": -0.0543,
      "wind_venue_sensitivity": 0.5,
      "home_lineup_pf_hr": null,
      "away_lineup_pf_hr": null,
      "lineup_pf_hr_diff": null,
      "lineup_pf_hr_residual": null,
      "has_lineups": false,
      "home_lineup_status": "UNKNOWN",
      "away_lineup_status": "UNKNOWN",
      "win_prob_home": null,
      "edge": null,
      "edge_side": null,
      "recommendation": null,
      "cgsi_tier": null,
      "consensus_ratio": null,
      "n_specialists_agree": null
    }
  ]
}