{
  "date": "2026-05-28",
  "generated_at": "2026-05-28T04:26:16.411423+00:00",
  "predictions_available": false,
  "model_version": "v2.0-approach-c",
  "games": [
    {
      "game_pk": 824272,
      "home_team": "DET",
      "away_team": "LAA",
      "venue": "Comerica Park",
      "home_pitcher": "Jack Flaherty",
      "away_pitcher": "Grayson Rodriguez",
      "game_time": "2026-05-28T17:10:00Z",
      "temperature_f": 69.6,
      "humidity_pct": 42.0,
      "wind_speed_mph": 12.6,
      "wind_carry_mph": 7.5,
      "air_density_index": 95.5,
      "dome_active": 0,
      "seasonal_pf_runs": 0.96,
      "daily_pf_runs": 0.9947,
      "daily_pf_hr": 1.1548,
      "pf_weather_delta_runs": 0.0347,
      "pf_weather_delta_hr": 0.1468,
      "wind_venue_sensitivity": 1.0,
      "home_lineup_pf_hr": null,
      "away_lineup_pf_hr": null,
      "lineup_pf_hr_diff": null,
      "lineup_pf_hr_residual": null,
      "has_lineups": false,
      "home_lineup_status": "UNKNOWN",
      "away_lineup_status": "UNKNOWN",
      "win_prob_home": null,
      "edge": null,
      "edge_side": null,
      "recommendation": null,
      "cgsi_tier": null,
      "consensus_ratio": null,
      "n_specialists_agree": null
    },
    {
      "game_pk": 824595,
      "home_team": "CHW",
      "away_team": "MIN",
      "venue": "Rate Field",
      "home_pitcher": "Davis Martin",
      "away_pitcher": "Kendry Rojas",
      "game_time": "2026-05-28T18:10:00Z",
      "temperature_f": null,
      "humidity_pct": null,
      "wind_speed_mph": null,
      "wind_carry_mph": null,
      "air_density_index": null,
      "dome_active": 0,
      "seasonal_pf_runs": 1.0,
      "daily_pf_runs": null,
      "daily_pf_hr": null,
      "pf_weather_delta_runs": null,
      "pf_weather_delta_hr": null,
      "wind_venue_sensitivity": null,
      "home_lineup_pf_hr": null,
      "away_lineup_pf_hr": null,
      "lineup_pf_hr_diff": null,
      "lineup_pf_hr_residual": null,
      "has_lineups": false,
      "home_lineup_status": "UNKNOWN",
      "away_lineup_status": "UNKNOWN",
      "win_prob_home": null,
      "edge": null,
      "edge_side": null,
      "recommendation": null,
      "cgsi_tier": null,
      "consensus_ratio": null,
      "n_specialists_agree": null
    },
    {
      "game_pk": 824757,
      "home_team": "BOS",
      "away_team": "ATL",
      "venue": "Fenway Park",
      "home_pitcher": "Payton Tolle",
      "away_pitcher": "Chris Sale",
      "game_time": "2026-05-28T20:10:00Z",
      "temperature_f": 66.3,
      "humidity_pct": 51.0,
      "wind_speed_mph": 9.4,
      "wind_carry_mph": -8.8,
      "air_density_index": 98.1,
      "dome_active": 0,
      "seasonal_pf_runs": 1.03,
      "daily_pf_runs": 1.0031,
      "daily_pf_hr": 1.0692,
      "pf_weather_delta_runs": -0.0269,
      "pf_weather_delta_hr": -0.0123,
      "wind_venue_sensitivity": 1.0,
      "home_lineup_pf_hr": null,
      "away_lineup_pf_hr": null,
      "lineup_pf_hr_diff": null,
      "lineup_pf_hr_residual": null,
      "has_lineups": false,
      "home_lineup_status": "UNKNOWN",
      "away_lineup_status": "UNKNOWN",
      "win_prob_home": null,
      "edge": null,
      "edge_side": null,
      "recommendation": null,
      "cgsi_tier": null,
      "consensus_ratio": null,
      "n_specialists_agree": null
    },
    {
      "game_pk": 824834,
      "home_team": "BAL",
      "away_team": "TOR",
      "venue": "Oriole Park at Camden Yards",
      "home_pitcher": "Chris Bassitt",
      "away_pitcher": "Patrick Corbin",
      "game_time": "2026-05-28T22:35:00Z",
      "temperature_f": 67.6,
      "humidity_pct": 60.0,
      "wind_speed_mph": 8.0,
      "wind_carry_mph": -4.8,
      "air_density_index": 97.8,
      "dome_active": 0,
      "seasonal_pf_runs": 1.02,
      "daily_pf_runs": 0.9691,
      "daily_pf_hr": 1.0191,
      "pf_weather_delta_runs": -0.0509,
      "pf_weather_delta_hr": -0.0519,
      "wind_venue_sensitivity": 1.0,
      "home_lineup_pf_hr": null,
      "away_lineup_pf_hr": null,
      "lineup_pf_hr_diff": null,
      "lineup_pf_hr_residual": null,
      "has_lineups": false,
      "home_lineup_status": "UNKNOWN",
      "away_lineup_status": "UNKNOWN",
      "win_prob_home": null,
      "edge": null,
      "edge_side": null,
      "recommendation": null,
      "cgsi_tier": null,
      "consensus_ratio": null,
      "n_specialists_agree": null
    },
    {
      "game_pk": 823378,
      "home_team": "PIT",
      "away_team": "CHC",
      "venue": "PNC Park",
      "home_pitcher": "Paul Skenes",
      "away_pitcher": "Colin Rea",
      "game_time": "2026-05-28T22:40:00Z",
      "temperature_f": 68.4,
      "humidity_pct": 47.0,
      "wind_speed_mph": 10.1,
      "wind_carry_mph": -7.4,
      "air_density_index": 95.2,
      "dome_active": 0,
      "seasonal_pf_runs": 0.95,
      "daily_pf_runs": 0.9426,
      "daily_pf_hr": 0.9341,
      "pf_weather_delta_runs": -0.0074,
      "pf_weather_delta_hr": -0.0634,
      "wind_venue_sensitivity": 1.0,
      "home_lineup_pf_hr": null,
      "away_lineup_pf_hr": null,
      "lineup_pf_hr_diff": null,
      "lineup_pf_hr_residual": null,
      "has_lineups": false,
      "home_lineup_status": "UNKNOWN",
      "away_lineup_status": "UNKNOWN",
      "win_prob_home": null,
      "edge": null,
      "edge_side": null,
      "recommendation": null,
      "cgsi_tier": null,
      "consensus_ratio": null,
      "n_specialists_agree": null
    },
    {
      "game_pk": 822896,
      "home_team": "TEX",
      "away_team": "HOU",
      "venue": "Globe Life Field",
      "home_pitcher": "Nathan Eovaldi",
      "away_pitcher": "Spencer Arrighetti",
      "game_time": "2026-05-29T00:05:00Z",
      "temperature_f": 82.0,
      "humidity_pct": 68.0,
      "wind_speed_mph": 1.4,
      "wind_carry_mph": -1.4,
      "air_density_index": 93.0,
      "dome_active": 0,
      "seasonal_pf_runs": 1.01,
      "daily_pf_runs": 1.0411,
      "daily_pf_hr": 1.1415,
      "pf_weather_delta_runs": 0.0311,
      "pf_weather_delta_hr": 0.081,
      "wind_venue_sensitivity": 0.5,
      "home_lineup_pf_hr": null,
      "away_lineup_pf_hr": null,
      "lineup_pf_hr_diff": null,
      "lineup_pf_hr_residual": null,
      "has_lineups": false,
      "home_lineup_status": "UNKNOWN",
      "away_lineup_status": "UNKNOWN",
      "win_prob_home": null,
      "edge": null,
      "edge_side": null,
      "recommendation": null,
      "cgsi_tier": null,
      "consensus_ratio": null,
      "n_specialists_agree": null
    }
  ]
}